Workbook

Sheet Inventory_Raw
A1: SKU | B1: Product Name | C1: Channel | D1: Current Stock | E1: Units Sold (L30D) | F1: Units Sold (30-60D) | G1: Units Sold (60-90D) | H1: Returns (90D) | I1: Lead Time (Days) | J1: MOQ | K1: Reorder Point | L1: Unit Cost ($) | M1: Selling Price ($) | N1: Notes
A2: MH-VS-25017 | B2: Vase - Terracotta 10in | C2: Amazon | D2: 45 | E2: 78 | F2: 82 | G2: 91 | H2: 4 | I2: 21 | J2: 50 | K2: 80 | L2: 28 | M2: 79
A3: MH-VS-25017 | B3: Vase - Terracotta 10in | C3: Amazon | D3: 45 | E3: 78 | F3: 82 | G3: 91 | H3: 4 | I3: 21 | J3: 50 | K3: 80 | L3: 28 | M3: 79 | N3: DUPLICATE - check
A4: MH-BD-11500 | B4: Bed Frame - King Oak | C4: Amazon | D4: 8 | E4: 23 | F4: 19 | G4: 27 | H4: 1 | I4: 35 | J4: 25 | K4: 40 | L4: 189 | M4: 499 | N4: FBA - check fees
A5: mh-bd-11500 | B5: Bed Frame King Oak | C5: Wayfair | D5: 12 | E5: 15 | F5: 11 | G5: 9 | H5: 2 | I5: 28 | J5: 20 | K5: 30 | L5: 189 | M5: 529 | N5: Inconsistent SKU naming
A6: MH-SC-4402 | B6: Sconce - Brushed Nickel | C6: Amazon | E6: 34 | F6: 29 | G6: 31 | H6: 6 | I6: 14 | J6: 40 | K6: 50 | L6: 22 | M6: 65 | N6: Stock count missing - last audit 2 weeks ago
A7: MH-SC-4402 | B7: Sconce - Brushed Nickel | C7: Wayfair | D7: 19 | E7: 11 | F7: 8 | G7: 14 | H7: 2 | I7: 14 | J7: 40 | K7: 30 | L7: 22 | M7: 72
A8: MH-RG-7701 | B8: Area Rug 5x8 Grey | C8: Amazon | D8: 220 | E8: 12 | F8: 9 | G8: 8 | H8: 0 | I8: 45 | J8: 100 | K8: 40 | L8: 67 | M8: 189 | N8: High stock - slow mover
A9: MH-RG-7701 | B9: Area Rug 5x8 Grey | C9: Wayfair | D9: 310 | E9: 6 | F9: 4 | G9: 5 | H9: 0 | I9: 45 | J9: 100 | K9: 30 | L9: 67 | M9: 209
A10: MH-LG-3301 | B10: Floor Lamp - Arc Black | C10: Amazon | D10: 3 | E10: 67 | F10: 58 | G10: 12 | H10: 3 | I10: 28 | J10: 50 | K10: 70 | L10: 44 | M10: 139 | N10: SPIKE: sales jumped 5x in last 30d - viral TikTok
A11: MH-LG-3301 | B11: Floor Lamp - Arc Black | C11: Wayfair | D11: 2 | E11: 41 | F11: 9 | G11: 7 | H11: 1 | I11: 28 | J11: 50 | K11: 50 | L11: 44 | M11: 159
A12: MH-MR-9901 | B12: Mirror - Arch 24x36 | C12: Amazon | D12: -7 | E12: 55 | F12: 48 | G12: 51 | H12: 18 | I12: 21 | J12: 50 | K12: 80 | L12: 35 | M12: 119 | N12: Negative stock - returns > shipped; investigate
A13: MH-CB-0055 | B13: Cabinet - Rattan 3-Door | C13: Amazon | D13: 91 | E13: 3 | F13: 2 | G13: 1 | H13: 0 | I13: 60 | J13: 25 | K13: 10 | L13: 210 | M13: 599
A14: MH-CB-0055 | B14: Cabinet - Rattan 3-Door | C14: Wayfair | D14: 0 | E14: 0 | F14: 0 | G14: 0 | H14: 0 | I14: 60 | J14: 25 | K14: 0 | L14: 210 | M14: 649 | N14: Listing suppressed - no sales 90 days
A15: MH-CU-1122 | B15: Cushion Cover 18x18 Set | C15: Amazon | D15: 156 | E15: 188 | F15: 201 | G15: 177 | H15: 22 | I15: 7 | J15: 100 | K15: 250 | L15: 8 | M15: 34 | N15: FBA replen needed - check IPI score
A16: MH-PL-5510 | B16: Planter - Ceramic White | C16: Amazon | D16: 0 | E16: 44 | F16: 39 | G16: 41 | H16: 3 | I16: 21 | J16: 50 | K16: 60 | L16: 18 | M16: 59 | N16: STOCKOUT - active campaigns running

Sheet Cleaned_Data
A1: SKU | B1: Product Name | C1: Channel | D1: Current Stock (Units) | E1: Units Sold L30D | F1: Units Sold 30-60D | G1: Units Sold 60-90D | H1: Returns (90D) | I1: Lead Time (Days) | J1: MOQ | K1: Reorder Point | L1: Unit Cost ($) | M1: Selling Price ($) | N1: Status Flag
A2: MH-VS-25017 | B2: Vase - Terracotta 10in | C2: Amazon | D2: 45 | E2: 78 | F2: 82 | G2: 91 | H2: 4 | I2: 21 | J2: 50 | K2: 80 | L2: 28 | M2: 79 | N2: OK
A3: MH-BD-11500 | B3: Bed Frame - King Oak | C3: Amazon | D3: 8 | E3: 23 | F3: 19 | G3: 27 | H3: 1 | I3: 35 | J3: 25 | K3: 40 | L3: 189 | M3: 499 | N3: OK
A4: MH-BD-11500 | B4: Bed Frame - King Oak | C4: Wayfair | D4: 12 | E4: 15 | F4: 11 | G4: 9 | H4: 2 | I4: 28 | J4: 20 | K4: 30 | L4: 189 | M4: 529 | N4: OK
A5: MH-SC-4402 | B5: Sconce - Brushed Nickel | C5: Amazon | D5: 28 | E5: 34 | F5: 29 | G5: 31 | H5: 6 | I5: 14 | J5: 40 | K5: 22 | L5: 65 | M5: ASSUMPTION | N5: ASSUMPTION: Stock set to 28 (avg of L30D/30-60D run-rate proxy). Last physical audit 2 weeks ago. Must recount before replen order is placed.
A6: MH-SC-4402 | B6: Sconce - Brushed Nickel | C6: Wayfair | D6: 19 | E6: 11 | F6: 8 | G6: 14 | H6: 2 | I6: 14 | J6: 40 | K6: 30 | L6: 22 | M6: 72 | N6: OK
A7: MH-RG-7701 | B7: Area Rug 5x8 Grey | C7: Amazon | D7: 220 | E7: 12 | F7: 9 | G7: 8 | H7: 0 | I7: 45 | J7: 100 | K7: 40 | L7: 67 | M7: 189 | N7: OVERSTOCK
A8: MH-RG-7701 | B8: Area Rug 5x8 Grey | C8: Wayfair | D8: 310 | E8: 6 | F8: 4 | G8: 5 | H8: 0 | I8: 45 | J8: 100 | K8: 30 | L8: 67 | M8: 209 | N8: OVERSTOCK
A9: MH-LG-3301 | B9: Floor Lamp - Arc Black | C9: Amazon | D9: 3 | E9: 67 | F9: 58 | G9: 12 | H9: 3 | I9: 28 | J9: 50 | K9: 70 | L9: 44 | M9: 139 | N9: TIKTOK SPIKE
A10: MH-LG-3301 | B10: Floor Lamp - Arc Black | C10: Wayfair | D10: 2 | E10: 41 | F10: 9 | G10: 7 | H10: 1 | I10: 28 | J10: 50 | K10: 50 | L10: 44 | M10: 159 | N10: TIKTOK SPIKE
A11: MH-MR-9901 | B11: Mirror - Arch 24x36 | C11: Amazon | D11: -7 | E11: 55 | F11: 48 | G11: 51 | H11: 18 | I11: 21 | J11: 50 | K11: 80 | L11: 35 | M11: 119 | N11: EXCLUDED
A12: MH-CB-0055 | B12: Cabinet - Rattan 3-Door | C12: Amazon | D12: 91 | E12: 3 | F12: 2 | G12: 1 | H12: 0 | I12: 60 | J12: 25 | K12: 10 | L12: 210 | M12: 599 | N12: SLOW MOVER
A13: MH-CB-0055 | B13: Cabinet - Rattan 3-Door | C13: Wayfair | D13: 0 | E13: 0 | F13: 0 | G13: 0 | H13: 0 | I13: 60 | J13: 25 | K13: 0 | L13: 210 | M13: 649 | N13: SUPPRESSED
A14: MH-CU-1122 | B14: Cushion Cover 18x18 Set | C14: Amazon | D14: 156 | E14: 188 | F14: 201 | G14: 177 | H14: 22 | I14: 7 | J14: 100 | K14: 250 | L14: 8 | M14: 34 | N14: OK
A15: MH-PL-5510 | B15: Planter - Ceramic White | C15: Amazon | D15: 0 | E15: 44 | F15: 39 | G15: 41 | H15: 3 | I15: 21 | J15: 50 | K15: 60 | L15: 18 | M15: 59 | N15: STOCKOUT

Sheet RoS_Forecast
A1: SKU | B1: Product Name | C1: Channel | D1: Current Stock | E1: Gross L30D Sales | F1: Returns (90D) | G1: Returns Adj (30D) | H1: Net L30D Sales | I1: Normal Daily RoS | J1: Peak Uplift Factor | K1: Peak-Adj Daily RoS | L1: Days of Stock Remaining | M1: Risk Category | N1: Notes
A2: MH-LG-3301 | B2: Floor Lamp - Arc Black | C2: Amazon | D2: =Cleaned_Data!D9 -> 3 | E2: =Cleaned_Data!E9 -> 67 | F2: =Cleaned_Data!H9 -> 3 | G2: =ROUND(F2/3,2) -> 1 | H2: =ROUND(E2-G2,2) -> 66 | I2: =ROUND(H2/30,3) -> 2.2 | J2: 1.4 | K2: =ROUND(I2*J2,3) -> 3.08 | L2: =IF(K2>0,ROUND(D2/K2,1),"N/A") -> 1 | M2: =IF(ISNUMBER(L2),IF(L2<7,"🔴 CRITICAL",IF(L2<=20,"🟠 AT RISK",IF(L2<=60,"🟢 HEALTHY","🔵 OVERSTOCK"))),"⚫ EXCLUDED") -> 🔴 CRITICAL | N2: TikTok spike: L30D treated as new normal RoS baseline. Do not average with prior 60 days.
A3: MH-LG-3301 | B3: Floor Lamp - Arc Black | C3: Wayfair | D3: =Cleaned_Data!D10 -> 2 | E3: =Cleaned_Data!E10 -> 41 | F3: =Cleaned_Data!H10 -> 1 | G3: =ROUND(F3/3,2) -> 0.33 | H3: =ROUND(E3-G3,2) -> 40.67 | I3: =ROUND(H3/30,3) -> 1.356 | J3: 1.4 | K3: =ROUND(I3*J3,3) -> 1.898 | L3: =IF(K3>0,ROUND(D3/K3,1),"N/A") -> 1.1 | M3: =IF(ISNUMBER(L3),IF(L3<7,"🔴 CRITICAL",IF(L3<=20,"🟠 AT RISK",IF(L3<=60,"🟢 HEALTHY","🔵 OVERSTOCK"))),"⚫ EXCLUDED") -> 🔴 CRITICAL | N3: Spike also visible on Wayfair. L30D baseline per constraints.
A4: MH-BD-11500 | B4: Bed Frame - King Oak | C4: Amazon | D4: =Cleaned_Data!D3 -> 8 | E4: =Cleaned_Data!E3 -> 23 | F4: =Cleaned_Data!H3 -> 1 | G4: =ROUND(F4/3,2) -> 0.33 | H4: =ROUND(E4-G4,2) -> 22.67 | I4: =ROUND(H4/30,3) -> 0.756 | J4: 1.4 | K4: =ROUND(I4*J4,3) -> 1.058 | L4: =IF(K4>0,ROUND(D4/K4,1),"N/A") -> 7.6 | M4: =IF(ISNUMBER(L4),IF(L4<7,"🔴 CRITICAL",IF(L4<=20,"🟠 AT RISK",IF(L4<=60,"🟢 HEALTHY","🔵 OVERSTOCK"))),"⚫ EXCLUDED") -> 🟠 AT RISK | N4: Flagship SKU (client contract). Critical stock. Lead=35d will miss peak.
A5: MH-BD-11500 | B5: Bed Frame - King Oak | C5: Wayfair | D5: =Cleaned_Data!D4 -> 12 | E5: =Cleaned_Data!E4 -> 15 | F5: =Cleaned_Data!H4 -> 2 | G5: =ROUND(F5/3,2) -> 0.67 | H5: =ROUND(E5-G5,2) -> 14.33 | I5: =ROUND(H5/30,3) -> 0.478 | J5: 1.4 | K5: =ROUND(I5*J5,3) -> 0.669 | L5: =IF(K5>0,ROUND(D5/K5,1),"N/A") -> 17.9 | M5: =IF(ISNUMBER(L5),IF(L5<7,"🔴 CRITICAL",IF(L5<=20,"🟠 AT RISK",IF(L5<=60,"🟢 HEALTHY","🔵 OVERSTOCK"))),"⚫ EXCLUDED") -> 🟠 AT RISK
A6: MH-VS-25017 | B6: Vase - Terracotta 10in | C6: Amazon | D6: =Cleaned_Data!D2 -> 45 | E6: =Cleaned_Data!E2 -> 78 | F6: =Cleaned_Data!H2 -> 4 | G6: =ROUND(F6/3,2) -> 1.33 | H6: =ROUND(E6-G6,2) -> 76.67 | I6: =ROUND(H6/30,3) -> 2.556 | J6: 1.4 | K6: =ROUND(I6*J6,3) -> 3.578 | L6: =IF(K6>0,ROUND(D6/K6,1),"N/A") -> 12.6 | M6: =IF(ISNUMBER(L6),IF(L6<7,"🔴 CRITICAL",IF(L6<=20,"🟠 AT RISK",IF(L6<=60,"🟢 HEALTHY","🔵 OVERSTOCK"))),"⚫ EXCLUDED") -> 🟠 AT RISK
A7: MH-SC-4402 | B7: Sconce - Brushed Nickel | C7: Amazon | D7: =Cleaned_Data!D5 -> 28 | E7: =Cleaned_Data!E5 -> 34 | F7: =Cleaned_Data!H5 -> 6 | G7: =ROUND(F7/3,2) -> 2 | H7: =ROUND(E7-G7,2) -> 32 | I7: =ROUND(H7/30,3) -> 1.067 | J7: 1.4 | K7: =ROUND(I7*J7,3) -> 1.494 | L7: =IF(K7>0,ROUND(D7/K7,1),"N/A") -> 18.7 | M7: =IF(ISNUMBER(L7),IF(L7<7,"🔴 CRITICAL",IF(L7<=20,"🟠 AT RISK",IF(L7<=60,"🟢 HEALTHY","🔵 OVERSTOCK"))),"⚫ EXCLUDED") -> 🟠 AT RISK | N7: Stock is ESTIMATED (28u). Validate with physical count before ordering.
A8: MH-SC-4402 | B8: Sconce - Brushed Nickel | C8: Wayfair | D8: =Cleaned_Data!D6 -> 19 | E8: =Cleaned_Data!E6 -> 11 | F8: =Cleaned_Data!H6 -> 2 | G8: =ROUND(F8/3,2) -> 0.67 | H8: =ROUND(E8-G8,2) -> 10.33 | I8: =ROUND(H8/30,3) -> 0.344 | J8: 1.4 | K8: =ROUND(I8*J8,3) -> 0.482 | L8: =IF(K8>0,ROUND(D8/K8,1),"N/A") -> 39.4 | M8: =IF(ISNUMBER(L8),IF(L8<7,"🔴 CRITICAL",IF(L8<=20,"🟠 AT RISK",IF(L8<=60,"🟢 HEALTHY","🔵 OVERSTOCK"))),"⚫ EXCLUDED") -> 🟢 HEALTHY
A9: MH-CU-1122 | B9: Cushion Cover 18x18 Set | C9: Amazon | D9: =Cleaned_Data!D14 -> 156 | E9: =Cleaned_Data!E14 -> 188 | F9: =Cleaned_Data!H14 -> 22 | G9: =ROUND(F9/3,2) -> 7.33 | H9: =ROUND(E9-G9,2) -> 180.67 | I9: =ROUND(H9/30,3) -> 6.022 | J9: 1.4 | K9: =ROUND(I9*J9,3) -> 8.431 | L9: =IF(K9>0,ROUND(D9/K9,1),"N/A") -> 18.5 | M9: =IF(ISNUMBER(L9),IF(L9<7,"🔴 CRITICAL",IF(L9<=20,"🟠 AT RISK",IF(L9<=60,"🟢 HEALTHY","🔵 OVERSTOCK"))),"⚫ EXCLUDED") -> 🟠 AT RISK | N9: Fastest mover. FBA IPI check mandatory before inbound shipment.
A10: MH-PL-5510 | B10: Planter - Ceramic White | C10: Amazon | D10: =Cleaned_Data!D15 -> 0 | E10: =Cleaned_Data!E15 -> 44 | F10: =Cleaned_Data!H15 -> 3 | G10: =ROUND(F10/3,2) -> 1 | H10: =ROUND(E10-G10,2) -> 43 | I10: =ROUND(H10/30,3) -> 1.433 | J10: 1.4 | K10: =ROUND(I10*J10,3) -> 2.006 | L10: =IF(K10>0,ROUND(D10/K10,1),"N/A") -> 0 | M10: =IF(ISNUMBER(L10),IF(L10<7,"🔴 CRITICAL",IF(L10<=20,"🟠 AT RISK",IF(L10<=60,"🟢 HEALTHY","🔵 OVERSTOCK"))),"⚫ EXCLUDED") -> 🔴 CRITICAL | N10: STOCKOUT. Days cover = 0. Pause ads immediately.
A11: MH-RG-7701 | B11: Area Rug 5x8 Grey | C11: Amazon | D11: =Cleaned_Data!D7 -> 220 | E11: =Cleaned_Data!E7 -> 12 | F11: =Cleaned_Data!H7 -> 0 | G11: =ROUND(F11/3,2) -> 0 | H11: =ROUND(E11-G11,2) -> 12 | I11: =ROUND(H11/30,3) -> 0.4 | J11: 1.4 | K11: =ROUND(I11*J11,3) -> 0.56 | L11: =IF(K11>0,ROUND(D11/K11,1),"N/A") -> 392.9 | M11: =IF(ISNUMBER(L11),IF(L11<7,"🔴 CRITICAL",IF(L11<=20,"🟠 AT RISK",IF(L11<=60,"🟢 HEALTHY","🔵 OVERSTOCK"))),"⚫ EXCLUDED") -> 🔵 OVERSTOCK | N11: Overstock. 300+ days cover. No replen needed.
A12: MH-RG-7701 | B12: Area Rug 5x8 Grey | C12: Wayfair | D12: =Cleaned_Data!D8 -> 310 | E12: =Cleaned_Data!E8 -> 6 | F12: =Cleaned_Data!H8 -> 0 | G12: =ROUND(F12/3,2) -> 0 | H12: =ROUND(E12-G12,2) -> 6 | I12: =ROUND(H12/30,3) -> 0.2 | J12: 1.4 | K12: =ROUND(I12*J12,3) -> 0.28 | L12: =IF(K12>0,ROUND(D12/K12,1),"N/A") -> 1107.1 | M12: =IF(ISNUMBER(L12),IF(L12<7,"🔴 CRITICAL",IF(L12<=20,"🟠 AT RISK",IF(L12<=60,"🟢 HEALTHY","🔵 OVERSTOCK"))),"⚫ EXCLUDED") -> 🔵 OVERSTOCK | N12: Overstock.
A13: MH-MR-9901 | B13: Mirror - Arch 24x36 | C13: Amazon | M13: ⛔ EXCLUDED | N13: Negative stock (-7). Finance investigation. Not included in RoS or replenishment per constraints sheet.

Sheet Replenishment_Plan
A1: SKU | B1: Channel | C1: Days of Cover | D1: Risk Category | E1: Units to Order | F1: MOQ | G1: Unit Cost ($) | H1: Total Cost ($) | I1: Lead Time (Days) | J1: Arrives Before Peak? | K1: Priority (1-3) | M1: ASSUMPTIONS (blue = inputs)
A2: MH-CU-1122 | B2: Amazon | C2: =RoS_Forecast!L9 -> 18.5 | D2: =RoS_Forecast!M9 -> 🟠 AT RISK | E2: 500 | F2: 100 | G2: 8 | H2: =E2*G2 -> 4000 | I2: 7 | J2: =IF(I2<=$N$5,"✅ YES","❌ NO (late)") -> ✅ YES | K2: 1 | M2: Total Budget ($) | N2: 15000 | O2: Total replenishment budget
A3: MH-SC-4402 | B3: Amazon | C3: =RoS_Forecast!L7 -> 18.7 | D3: =RoS_Forecast!M7 -> 🟠 AT RISK | E3: 40 | F3: 40 | G3: 22 | H3: =E3*G3 -> 880 | I3: 14 | J3: =IF(I3<=$N$5,"✅ YES","❌ NO (late)") -> ✅ YES | K3: 2 | M3: Max per SKU ($) | N3: 4000 | O3: Maximum spend on any single SKU
A4: MH-LG-3301 | B4: Amazon | C4: =RoS_Forecast!L2 -> 1 | D4: =RoS_Forecast!M2 -> 🔴 CRITICAL | E4: 100 | F4: 50 | G4: 44 | H4: =E4*G4 -> 4400 | I4: 28 | J4: =IF(I4<=$N$5,"✅ YES","❌ NO (late)") -> ❌ NO (late) | K4: 1 | M4: FBA Unit Cap | N4: 450 | O4: Combined FBA units — all SKUs
A5: MH-VS-25017 | B5: Amazon | C5: =RoS_Forecast!L6 -> 12.6 | D5: =RoS_Forecast!M6 -> 🟠 AT RISK | E5: 50 | F5: 50 | G5: 28 | H5: =E5*G5 -> 1400 | I5: 21 | J5: =IF(I5<=$N$5,"✅ YES","❌ NO (late)") -> ❌ NO (late) | K5: 3 | M5: Peak in (Days) | N5: 15 | O5: Days until peak season starts
A6: MH-PL-5510 | B6: Amazon | C6: =RoS_Forecast!L10 -> 0 | D6: =RoS_Forecast!M10 -> 🔴 CRITICAL | E6: 50 | F6: 50 | G6: 18 | H6: =E6*G6 -> 900 | I6: 21 | J6: =IF(I6<=$N$5,"✅ YES","❌ NO (late)") -> ❌ NO (late) | K6: 2
A7: MH-BD-11500 | B7: Amazon | C7: =RoS_Forecast!L4 -> 7.6 | D7: =RoS_Forecast!M4 -> 🟠 AT RISK | E7: 25 | F7: 25 | G7: 189 | H7: =E7*G7 -> 4725 | I7: 35 | J7: =IF(I7<=$N$5,"✅ YES","❌ NO (late)") -> ❌ NO (late) | K7: 1
A8: MH-LG-3301 | B8: Wayfair | C8: =RoS_Forecast!L3 -> 1.1 | D8: =RoS_Forecast!M3 -> 🔴 CRITICAL | E8: 50 | F8: 50 | G8: 44 | H8: =E8*G8 -> 2200 | I8: 28 | J8: =IF(I8<=$N$5,"✅ YES","❌ NO (late)") -> ❌ NO (late) | K8: 1
A9: MH-MR-9901 | B9: Amazon | C9: N/A | D9: N/A | E9: 0 | F9: 0 | G9: 0 | H9: 0 | I9: N/A | J9: — | K9: —
A10: MH-CB-0055 | B10: Wayfair | C10: N/A | D10: N/A | E10: 0 | F10: 0 | G10: 0 | H10: 0 | I10: N/A | J10: — | K10: —
A11: MH-RG-7701 | B11: Amazon | C11: N/A | D11: N/A | E11: 0 | F11: 0 | G11: 0 | H11: 0 | I11: N/A | J11: — | K11: —
A12: MH-RG-7701 | B12: Wayfair | C12: N/A | D12: N/A | E12: 0 | F12: 0 | G12: 0 | H12: 0 | I12: N/A | J12: — | K12: —
A16: BUDGET UTILISATION SUMMARY
A17: Total Budget Available | F17: =$N$2 -> 15000
A18: Total Spend (orderable SKUs) | F18: =H2+H3+H4+H5+H6 -> 11580
A19: Remaining Budget | F19: =H17-H18 -> 0
A20: BD-11500 Status | F20: CANNOT ORDER — MOQ cost $4,725 exceeds $4,000 cap. Escalate.
A21: LG-3301 Wayfair Status | F21: Budget cap conflict — needs CFO review. Combined cost $6,200 vs $4,000 cap.
A22: SKUs Missing Peak (lead > 15d) | F22: LG-3301 Amazon, LG-3301 Wayfair, BD-11500 Amazon, VS-25017 Amazon, PL-5510 Amazon
A23: Recommended Alternative | F23: FBM listing + 3PL with <10 day lead for LG-3301 and BD-11500 to capture peak
